genieai/__init__.py
genieai-0.0.1.dev0.dist-info/METADATA
genieai-0.0.1.dev0.dist-info/WHEEL
genieai-0.0.1.dev0.dist-info/top_level.txt
genieai-0.0.1.dev0.dist-info/RECORD
